contextualized_topic_models/__init__.py
contextualized_topic_models/contextualized_topic_models.py
contextualized_topic_models/datasets/__init__.py
contextualized_topic_models/datasets/dataset.py
contextualized_topic_models/evaluation/__init__.py
contextualized_topic_models/evaluation/measures.py
contextualized_topic_models/evaluation/rbo/__init__.py
contextualized_topic_models/evaluation/rbo/rbo.py
contextualized_topic_models/models/__init__.py
contextualized_topic_models/models/ctm.py
contextualized_topic_models/models/kitty_classifier.py
contextualized_topic_models/networks/__init__.py
contextualized_topic_models/networks/decoding_network.py
contextualized_topic_models/networks/inference_network.py
contextualized_topic_models/utils/__init__.py
contextualized_topic_models/utils/data_preparation.py
contextualized_topic_models/utils/preprocessing.py
contextualized_topic_models/utils/early_stopping/__init__.py
contextualized_topic_models/utils/early_stopping/early_stopping.py
contextualized_topic_models-2.6.1.dist-info/licenses/AUTHORS.rst
contextualized_topic_models-2.6.1.dist-info/licenses/LICENSE
contextualized_topic_models-2.6.1.dist-info/METADATA
contextualized_topic_models-2.6.1.dist-info/WHEEL
contextualized_topic_models-2.6.1.dist-info/top_level.txt
contextualized_topic_models-2.6.1.dist-info/RECORD
