Metadata-Version: 2.4
Name: contextualized_topic_models
Version: 2.6.1
Summary: Contextualized Topic Models
Home-page: https://github.com/MilaNLProc/contextualized-topic-models
Author: Federico Bianchi
Author-email: f.bianchi@unibocconi.it
License: MIT license
Keywords: contextualized_topic_models
Classifier: Development Status :: 2 - Pre-Alpha
Classifier: Intended Audience :: Developers
Classifier: License :: OSI Approved :: MIT License
Classifier: Natural Language :: English
Classifier: Programming Language :: Python :: 3.10
Classifier: Programming Language :: Python :: 3.11
Classifier: Programming Language :: Python :: 3.12
Requires-Python: >=3.10
License-File: LICENSE
License-File: AUTHORS.rst
Requires-Dist: numpy>=1.24.0
Requires-Dist: torchvision>=0.15.0
Requires-Dist: torch>=2.0.0
Requires-Dist: gensim>=4.3.3
Requires-Dist: sentence-transformers>=2.2.0
Requires-Dist: wordcloud>=1.9.0
Requires-Dist: matplotlib>=3.6.0
Requires-Dist: nltk>=3.8.0
Requires-Dist: tqdm>=4.64.0
Requires-Dist: scipy>=1.10.0
Requires-Dist: ipywidgets>=8.0.0
Requires-Dist: ipython_genutils>=0.2.0
Dynamic: author
Dynamic: author-email
Dynamic: classifier
Dynamic: description
Dynamic: description-content-type
Dynamic: home-page
Dynamic: keywords
Dynamic: license
Dynamic: license-file
Dynamic: requires-dist
Dynamic: requires-python
Dynamic: summary
